specfabpy/__init__.py
specfabpy/common.py
specfabpy/constants.py
specfabpy/discrete.py
specfabpy/integrator.py
specfabpy/plotting.py
specfabpy/ratefactor.py
specfabpy/specfabpy.cpython-310-x86_64-linux-gnu.so
specfabpy/specfabpy.cpython-311-x86_64-linux-gnu.so
specfabpy/specfabpy.cpython-312-x86_64-linux-gnu.so
specfabpy/specfabpy.cpython-313-x86_64-linux-gnu.so
specfabpy/specfabpy.cpython-38-x86_64-linux-gnu.so
specfabpy/specfabpy.cpython-39-x86_64-linux-gnu.so
specfabpy/statespace.py
specfabpy/fenics/CPO.py
specfabpy/fenics/FSE.py
specfabpy/fenics/__init__ .py
specfabpy/fenics/enhancementfactor.py
specfabpy/fenics/ice.py
specfabpy/fenics/olivine.py
specfabpy/fenics/rheology.py
specfabpy/fenics/steadyCPO.py
specfabpy/fenics/tools.py
specfabpy/firedrake/ice.py
specfabpy/firedrake/mesh.py
specfabpy/tamm/GTMcore.py
specfabpy/tamm/layer.py
specfabpy/tamm/layer_PPJ.py
specfabpy/tamm/layerstack.py
specfabpy.libs/libgfortran-83c28eba.so.5.0.0
specfabpy.libs/libmvec-2-583a17db.28.so
specfabpy.libs/libquadmath-2284e583.so.0.0.0
specfabpy-2025.10.2.dist-info/METADATA
specfabpy-2025.10.2.dist-info/WHEEL
specfabpy-2025.10.2.dist-info/top_level.txt
specfabpy-2025.10.2.dist-info/RECORD
