Metadata-Version: 2.1
Name: specfabpy
Version: 2025.10.2
Summary: specfab Python module
Home-page: https://github.com/nicholasmr/specfab
Author: Nicholas M. Rathmann and David A. Lilien
Author-email: rathmann@nbi.ku.dk
Requires-Python: >=3.8
Requires-Dist: numpy>=1.24
